Workbook
Name _Int_3zCWM0Ms: 'categories 2'!#REF!

Sheet data
A1: DOI | B1: Authors | C1: Year | D1: Title | E1: Journal | F1: URL | G1: Citations | H1: Article per journal | I1: Study number | J1: General Notes | K1: Measure number | L1: Measure name | M1: How it is measured | N1: What is measured | O1: how-what alignment | P1: Used recent technology (only for 'what'=behavior) | Q1: Used as DV (only for 'what'=behavior) | R1: Measure notes
A2: 10.1016/j.brat.2022.104101 | B2: Hornstein; Eisenberger | C2: 2022 | D2: Exploring the effect of loneliness on fear: Implications for the effect of COVID-19-induced social disconnection on anxiety | E2: Behaviour Research and Therapy | F2: https://doi.org/10.1016/j.brat.2022.104101 | G2: 8 | H2: 1 | I2: 3 | K2: 1 | L2: Skin Conductance Response (SCR) Screening | M2: Neuro/bio/physiological | N2: Subjective experience | O2: =IF(OR(AND(data!M2='categories 2'!A$2,data!N2='categories 2'!B$2), AND(data!M2='categories 2'!A$3,data!N2='categories 2'!B$3), AND(data!M2='categories 2'!A$4,data!N2='categories 2'!B$4), AND(data!M2='categories 2'!A$5,data!N2='categories 2'!B$5)), "aligned", "MISALIGNED") -> MISALIGNED
I3: 3 | K3: 2 | L3: UCLA Loneliness Scale v3 (Russell, 1996) | M3: Self report | N3: Subjective experience | O3: =IF(OR(AND(data!M3='categories 2'!A$2,data!N3='categories 2'!B$2), AND(data!M3='categories 2'!A$3,data!N3='categories 2'!B$3), AND(data!M3='categories 2'!A$4,data!N3='categories 2'!B$4), AND(data!M3='categories 2'!A$5,data!N3='categories 2'!B$5)), "aligned", "MISALIGNED") -> aligned
A4: 10.1016/j.brat.2023.104456 | B4: Burger; Andikkhash; Jäger; Anderbro; Blanken; Klintwall | C4: 2024 | D4: A novel approach for constructing personalized networks from longitudinal perceived causal relations | E4: Behaviour Research and Therapy | F4: https://doi.org/10.1016/j.brat.2023.104456 | G4: 3 | H4: 2 | I4: 1 | K4: 1 | L4: PHQ-9 (Kroenke et al., 2001) | M4: Self report | N4: Subjective experience | O4: =IF(OR(AND(data!M4='categories 2'!A$2,data!N4='categories 2'!B$2), AND(data!M4='categories 2'!A$3,data!N4='categories 2'!B$3), AND(data!M4='categories 2'!A$4,data!N4='categories 2'!B$4), AND(data!M4='categories 2'!A$5,data!N4='categories 2'!B$5)), "aligned", "MISALIGNED") -> aligned
I5: 1 | K5: 2 | L5: Daily assessments of L-PECAN (Klintwall et al., 2023) | M5: Self report | N5: Indeterminable | O5: =IF(OR(AND(data!M5='categories 2'!A$2,data!N5='categories 2'!B$2), AND(data!M5='categories 2'!A$3,data!N5='categories 2'!B$3), AND(data!M5='categories 2'!A$4,data!N5='categories 2'!B$4), AND(data!M5='categories 2'!A$5,data!N5='categories 2'!B$5)), "aligned", "MISALIGNED") -> MISALIGNED
A6: 10.1111/cdev.13157 | B6: Elenbaas | C6: 2019 | D6: Interwealth Contact and Young Children's Concern for Equity | E6: Child Development | F6: https://doi.org/10.1111/cdev.13157 | G6: 17 | H6: 1 | I6: 1 | K6: 1 | L6: Unnamed questions: "Wealth Preference and Perceptions" | M6: Self report | N6: Subjective experience | O6: =IF(OR(AND(data!M6='categories 2'!A$2,data!N6='categories 2'!B$2), AND(data!M6='categories 2'!A$3,data!N6='categories 2'!B$3), AND(data!M6='categories 2'!A$4,data!N6='categories 2'!B$4), AND(data!M6='categories 2'!A$5,data!N6='categories 2'!B$5)), "aligned", "MISALIGNED") -> aligned
I7: 1 | K7: 2 | L7: Unnamed Task: "Resource Allocation" | M7: Behavioral (frequency, duration, latency) | N7: Behavior | O7: =IF(OR(AND(data!M7='categories 2'!A$2,data!N7='categories 2'!B$2), AND(data!M7='categories 2'!A$3,data!N7='categories 2'!B$3), AND(data!M7='categories 2'!A$4,data!N7='categories 2'!B$4), AND(data!M7='categories 2'!A$5,data!N7='categories 2'!B$5)), "aligned", "MISALIGNED") -> aligned | P7: FALSE | Q7: Out of time
I8: 1 | K8: 3 | L8: Reasoning About Resource Allocation | M8: Self report | N8: Subjective experience | O8: =IF(OR(AND(data!M8='categories 2'!A$2,data!N8='categories 2'!B$2), AND(data!M8='categories 2'!A$3,data!N8='categories 2'!B$3), AND(data!M8='categories 2'!A$4,data!N8='categories 2'!B$4), AND(data!M8='categories 2'!A$5,data!N8='categories 2'!B$5)), "aligned", "MISALIGNED") -> aligned
I9: 1 | K9: 4 | L9: Unnamed questions: "Inter and Intra-wealth Contact" | M9: Self report | N9: Indeterminable | O9: =IF(OR(AND(data!M9='categories 2'!A$2,data!N9='categories 2'!B$2), AND(data!M9='categories 2'!A$3,data!N9='categories 2'!B$3), AND(data!M9='categories 2'!A$4,data!N9='categories 2'!B$4), AND(data!M9='categories 2'!A$5,data!N9='categories 2'!B$5)), "aligned", "MISALIGNED") -> MISALIGNED
A10: 10.1111/j.1467-8624.2012.01817.x | B10: Bascoe; Davies; Cummings | C10: 2012 | D10: Beyond Warmth and Conflict: The Developmental Utility of a Boundary Conceptualization of Sibling Relationship Processes | E10: Child Development | F10: https://doi.org/10.1111/j.1467-8624.2012.01817.x | G10: 17 | H10: 2 | I10: 1 | K10: 1 | L10: Emotional Symptoms subscale from the Self-Report Strengths and Difficulties Questionnaire (SDQ, Goodman, 2001) | M10: Self report | N10: Subjective experience | O10: =IF(OR(AND(data!M10='categories 2'!A$2,data!N10='categories 2'!B$2), AND(data!M10='categories 2'!A$3,data!N10='categories 2'!B$3), AND(data!M10='categories 2'!A$4,data!N10='categories 2'!B$4), AND(data!M10='categories 2'!A$5,data!N10='categories 2'!B$5)), "aligned", "MISALIGNED") -> aligned
I11: 1 | J11: Subjective, behavioral and physiological items! | K11: 2 | L11: Total Anxiety scale from the Revised Child Manifest Anxiety Scale (RCMAS) | M11: Self report | N11: Neuro/bio/physiology | O11: =IF(OR(AND(data!M11='categories 2'!A$2,data!N11='categories 2'!B$2), AND(data!M11='categories 2'!A$3,data!N11='categories 2'!B$3), AND(data!M11='categories 2'!A$4,data!N11='categories 2'!B$4), AND(data!M11='categories 2'!A$5,data!N11='categories 2'!B$5)), "aligned", "MISALIGNED") -> MISALIGNED
I12: 1 | K12: 3 | L12: Center for Epidemiological Studies Depression Scale (CES-D) | M12: Self report | N12: Behavior | O12: =IF(OR(AND(data!M12='categories 2'!A$2,data!N12='categories 2'!B$2), AND(data!M12='categories 2'!A$3,data!N12='categories 2'!B$3), AND(data!M12='categories 2'!A$4,data!N12='categories 2'!B$4), AND(data!M12='categories 2'!A$5,data!N12='categories 2'!B$5)), "aligned", "MISALIGNED") -> MISALIGNED | P12: FALSE | Q12: TRUE
I13: 1 | K13: 4 | L13: Delinquent scales from the respective Teacher Report Form and Child Behavior Checklist instruments (Achenbach, 1991) | M13: Self report | N13: Behavior | O13: =IF(OR(AND(data!M13='categories 2'!A$2,data!N13='categories 2'!B$2), AND(data!M13='categories 2'!A$3,data!N13='categories 2'!B$3), AND(data!M13='categories 2'!A$4,data!N13='categories 2'!B$4), AND(data!M13='categories 2'!A$5,data!N13='categories 2'!B$5)), "aligned", "MISALIGNED") -> MISALIGNED | P13: FALSE | Q13: TRUE
I14: 1 | K14: 5 | L14: Conduct Problems subscale of the SDQ | M14: Self report | N14: Behavior | O14: =IF(OR(AND(data!M14='categories 2'!A$2,data!N14='categories 2'!B$2), AND(data!M14='categories 2'!A$3,data!N14='categories 2'!B$3), AND(data!M14='categories 2'!A$4,data!N14='categories 2'!B$4), AND(data!M14='categories 2'!A$5,data!N14='categories 2'!B$5)), "aligned", "MISALIGNED") -> MISALIGNED | P14: FALSE | Q14: TRUE
I15: 1 | K15: 6 | L15: Social Problems subscales of the CBCL questionnaire | M15: Self report | N15: Behavior | O15: =IF(OR(AND(data!M15='categories 2'!A$2,data!N15='categories 2'!B$2), AND(data!M15='categories 2'!A$3,data!N15='categories 2'!B$3), AND(data!M15='categories 2'!A$4,data!N15='categories 2'!B$4), AND(data!M15='categories 2'!A$5,data!N15='categories 2'!B$5)), "aligned", "MISALIGNED") -> MISALIGNED | P15: Out of time | Q15: Out of time
I16: 1 | K16: 7 | L16: Social Problems subscales of the TRF questionnaire | M16: Self report | N16: Behavior | O16: =IF(OR(AND(data!M16='categories 2'!A$2,data!N16='categories 2'!B$2), AND(data!M16='categories 2'!A$3,data!N16='categories 2'!B$3), AND(data!M16='categories 2'!A$4,data!N16='categories 2'!B$4), AND(data!M16='categories 2'!A$5,data!N16='categories 2'!B$5)), "aligned", "MISALIGNED") -> MISALIGNED | P16: Out of time | Q16: Out of time
A17: 10.1177/2167702613484717 | B17: Schueller; Pérez-Stable; Muñoz | C17: 2013 | D17: A Mood Management Intervention in an Internet Stop Smoking Randomized Controlled Trial Does Not Prevent Depression | E17: Clinical Psychological Science | F17: https://doi.org/10.1177/2167702613484717 | G17: 4 | H17: 1 | I17: 1 | K17: 1 | L17: MDE Screener (Muñoz, 1998) | M17: Self report | N17: Behavior | O17: =IF(OR(AND(data!M17='categories 2'!A$2,data!N17='categories 2'!B$2), AND(data!M17='categories 2'!A$3,data!N17='categories 2'!B$3), AND(data!M17='categories 2'!A$4,data!N17='categories 2'!B$4), AND(data!M17='categories 2'!A$5,data!N17='categories 2'!B$5)), "aligned", "MISALIGNED") -> MISALIGNED | P17: FALSE | Q17: TRUE
I18: 1 | K18: 2 | L18: Center for Epidemiologic Studies Depression Scale (CESD; Radloff, 1977) | M18: Self report | N18: Behavior | O18: =IF(OR(AND(data!M18='categories 2'!A$2,data!N18='categories 2'!B$2), AND(data!M18='categories 2'!A$3,data!N18='categories 2'!B$3), AND(data!M18='categories 2'!A$4,data!N18='categories 2'!B$4), AND(data!M18='categories 2'!A$5,data!N18='categories 2'!B$5)), "aligned", "MISALIGNED") -> MISALIGNED | P18: FALSE | Q18: TRUE
I19: 1 | K19: 3 | L19: Website utilization | M19: Behavioral (frequency, duration, latency) | N19: Behavior | O19: =IF(OR(AND(data!M19='categories 2'!A$2,data!N19='categories 2'!B$2), AND(data!M19='categories 2'!A$3,data!N19='categories 2'!B$3), AND(data!M19='categories 2'!A$4,data!N19='categories 2'!B$4), AND(data!M19='categories 2'!A$5,data!N19='categories 2'!B$5)), "aligned", "MISALIGNED") -> aligned | P19: TRUE | Q19: Out of time
A20: 10.1177/2167702614553026 | B20: Lane; Sher | C20: 2015 | D20: Limits of Current Approaches to Diagnosis Severity Based on Criterion Counts | E20: Clinical Psychological Science | F20: https://doi.org/10.1177/2167702614553026 | G20: 68 | H20: 2 | I20: 1 | J20: Structured Interview | K20: 1 | L20: AUD Criteria (Alcohol Use Disorder and Associated Disabilities Interview Schedule-IV; Grant et al., 2003) | M20: Self report | N20: Behavior | O20: =IF(OR(AND(data!M20='categories 2'!A$2,data!N20='categories 2'!B$2), AND(data!M20='categories 2'!A$3,data!N20='categories 2'!B$3), AND(data!M20='categories 2'!A$4,data!N20='categories 2'!B$4), AND(data!M20='categories 2'!A$5,data!N20='categories 2'!B$5)), "aligned", "MISALIGNED") -> MISALIGNED | P20: FALSE | Q20: FALSE
I21: 1 | K21: 2 | L21: Drinking behavior (Dawson et al., 2005) | M21: Self report | N21: Behavior | O21: =IF(OR(AND(data!M21='categories 2'!A$2,data!N21='categories 2'!B$2), AND(data!M21='categories 2'!A$3,data!N21='categories 2'!B$3), AND(data!M21='categories 2'!A$4,data!N21='categories 2'!B$4), AND(data!M21='categories 2'!A$5,data!N21='categories 2'!B$5)), "aligned", "MISALIGNED") -> MISALIGNED | P21: FALSE | Q21: TRUE
I22: 1 | K22: 3 | L22: Measure of overall health and wellbeing, constructed from the SF12-V2 physical and mental functioning scales | M22: Self report | N22: Neuro/bio/physiology | O22: =IF(OR(AND(data!M22='categories 2'!A$2,data!N22='categories 2'!B$2), AND(data!M22='categories 2'!A$3,data!N22='categories 2'!B$3), AND(data!M22='categories 2'!A$4,data!N22='categories 2'!B$4), AND(data!M22='categories 2'!A$5,data!N22='categories 2'!B$5)), "aligned", "MISALIGNED") -> MISALIGNED
I23: 1 | K23: 4 | L23: Lifetime Axis I and Axis II Diagnoses | M23: Self report | N23: Indeterminable | O23: =IF(OR(AND(data!M23='categories 2'!A$2,data!N23='categories 2'!B$2), AND(data!M23='categories 2'!A$3,data!N23='categories 2'!B$3), AND(data!M23='categories 2'!A$4,data!N23='categories 2'!B$4), AND(data!M23='categories 2'!A$5,data!N23='categories 2'!B$5)), "aligned", "MISALIGNED") -> MISALIGNED
A24: 10.1016/j.cognition.2013.01.010 | B24: Wagner; Dobkins; Barner | C24: 2013 | D24: Slow mapping: Color word learning as a gradual inductive process | E24: Cognition | F24: https://doi.org/10.1016/j.cognition.2013.01.010 | G24: 34 | H24: 1 | I24: 1 | K24: 1 | L24: Fish task | M24: Behavioral (frequency, duration, latency) | N24: Mental ability or cognitive process | O24: =IF(OR(AND(data!M24='categories 2'!A$2,data!N24='categories 2'!B$2), AND(data!M24='categories 2'!A$3,data!N24='categories 2'!B$3), AND(data!M24='categories 2'!A$4,data!N24='categories 2'!B$4), AND(data!M24='categories 2'!A$5,data!N24='categories 2'!B$5)), "aligned", "MISALIGNED") -> MISALIGNED
I25: 1 | K25: 2 | L25: Book task | M25: Behavioral (frequency, duration, latency) | N25: Mental ability or cognitive process | O25: =IF(OR(AND(data!M25='categories 2'!A$2,data!N25='categories 2'!B$2), AND(data!M25='categories 2'!A$3,data!N25='categories 2'!B$3), AND(data!M25='categories 2'!A$4,data!N25='categories 2'!B$4), AND(data!M25='categories 2'!A$5,data!N25='categories 2'!B$5)), "aligned", "MISALIGNED") -> MISALIGNED
A26: 10.1016/j.cognition.2024.106051 | B26: Finiasz; Shore; Xu; Kushnir | C26: 2025 | D26: Children's cost-benefit analysis about agents who act for the greater good | E26: Cognition | F26: https://doi.org/10.1016/j.cognition.2024.106051 | G26: 0 | H26: 2 | I26: 2 | K26: 1 | L26: Prediction Question (likert scale) | M26: Self report | N26: Subjective experience | O26: =IF(OR(AND(data!M26='categories 2'!A$2,data!N26='categories 2'!B$2), AND(data!M26='categories 2'!A$3,data!N26='categories 2'!B$3), AND(data!M26='categories 2'!A$4,data!N26='categories 2'!B$4), AND(data!M26='categories 2'!A$5,data!N26='categories 2'!B$5)), "aligned", "MISALIGNED") -> aligned
I27: 2 | K27: 2 | L27: Permissibility Judgment (likert scale) | M27: Self report | N27: Subjective experience | O27: =IF(OR(AND(data!M27='categories 2'!A$2,data!N27='categories 2'!B$2), AND(data!M27='categories 2'!A$3,data!N27='categories 2'!B$3), AND(data!M27='categories 2'!A$4,data!N27='categories 2'!B$4), AND(data!M27='categories 2'!A$5,data!N27='categories 2'!B$5)), "aligned", "MISALIGNED") -> aligned
A28: 10.1525/collabra.128470 | B28: Sato; Gygax; Gabriel; Oakhill; Escasain | C28: 2025 | D28: Does Inclusive Language Increase the Visibility of Women, or Does It Simply Decrease the Visibility of Men? A Missing Piece of the Inclusive Language Jigsaw | E28: Collabra: Psychology | F28: https://doi.org/10.1525/collabra.128470 | G28: 2 | H28: 1 | I28: 1 | K28: 1 | L28: Unnamed questionnaire: Estimating the distribution of women and men in occupations | M28: Self report | N28: Subjective experience | O28: =IF(OR(AND(data!M28='categories 2'!A$2,data!N28='categories 2'!B$2), AND(data!M28='categories 2'!A$3,data!N28='categories 2'!B$3), AND(data!M28='categories 2'!A$4,data!N28='categories 2'!B$4), AND(data!M28='categories 2'!A$5,data!N28='categories 2'!B$5)), "aligned", "MISALIGNED") -> aligned
A29: 10.1525/collabra.117083 | B29: Folk; Yu; Dunn | C29: 2024 | D29: Can Chatbots Ever Provide More Social Connection Than Humans? | E29: Collabra: Psychology | F29: https://doi.org/10.1525/collabra.117083 | G29: 0 | H29: 2 | I29: 2 | K29: 1 | L29: Social connection single-item (created for this study) | M29: Self report | N29: Subjective experience | O29: =IF(OR(AND(data!M29='categories 2'!A$2,data!N29='categories 2'!B$2), AND(data!M29='categories 2'!A$3,data!N29='categories 2'!B$3), AND(data!M29='categories 2'!A$4,data!N29='categories 2'!B$4), AND(data!M29='categories 2'!A$5,data!N29='categories 2'!B$5)), "aligned", "MISALIGNED") -> aligned
I30: 2 | K30: 2 | L30: Positive affect SPANE (Diener et al., 2009) | M30: Self report | N30: Subjective experience | O30: =IF(OR(AND(data!M30='categories 2'!A$2,data!N30='categories 2'!B$2), AND(data!M30='categories 2'!A$3,data!N30='categories 2'!B$3), AND(data!M30='categories 2'!A$4,data!N30='categories 2'!B$4), AND(data!M30='categories 2'!A$5,data!N30='categories 2'!B$5)), "aligned", "MISALIGNED") -> aligned
I31: 2 | K31: 3 | L31: Feelings about experience (created for this study) | M31: Self report | N31: Subjective experience | O31: =IF(OR(AND(data!M31='categories 2'!A$2,data!N31='categories 2'!B$2), AND(data!M31='categories 2'!A$3,data!N31='categories 2'!B$3), AND(data!M31='categories 2'!A$4,data!N31='categories 2'!B$4), AND(data!M31='categories 2'!A$5,data!N31='categories 2'!B$5)), "aligned", "MISALIGNED") -> aligned
I32: 2 | K32: 4 | L32: Perceived Agency (Epley et al., 2008) | M32: Self report | N32: Subjective experience | O32: =IF(OR(AND(data!M32='categories 2'!A$2,data!N32='categories 2'!B$2), AND(data!M32='categories 2'!A$3,data!N32='categories 2'!B$3), AND(data!M32='categories 2'!A$4,data!N32='categories 2'!B$4), AND(data!M32='categories 2'!A$5,data!N32='categories 2'!B$5)), "aligned", "MISALIGNED") -> aligned
A33: 10.1037/dev0000712 | B33: Brod; Shing | C33: 2019 | D33: A boon and a bane: Comparing the effects of prior knowledge on memory across the lifespan. | E33: Developmental Psychology | F33: https://doi.org/10.1037/dev0000712 | G33: 38 | H33: 1 | I33: 1 | K33: 1 | L33: Congruency judgement test | M33: Test | N33: Mental ability or cognitive process | O33: =IF(OR(AND(data!M33='categories 2'!A$2,data!N33='categories 2'!B$2), AND(data!M33='categories 2'!A$3,data!N33='categories 2'!B$3), AND(data!M33='categories 2'!A$4,data!N33='categories 2'!B$4), AND(data!M33='categories 2'!A$5,data!N33='categories 2'!B$5)), "aligned", "MISALIGNED") -> aligned
I34: 1 | K34: 2 | L34: Memory test | M34: Test | N34: Mental ability or cognitive process | O34: =IF(OR(AND(data!M34='categories 2'!A$2,data!N34='categories 2'!B$2), AND(data!M34='categories 2'!A$3,data!N34='categories 2'!B$3), AND(data!M34='categories 2'!A$4,data!N34='categories 2'!B$4), AND(data!M34='categories 2'!A$5,data!N34='categories 2'!B$5)), "aligned", "MISALIGNED") -> aligned
I35: 1 | K35: 3 | L35: fMRI | M35: Neuro/bio/physiological | N35: Mental ability or cognitive process | O35: =IF(OR(AND(data!M35='categories 2'!A$2,data!N35='categories 2'!B$2), AND(data!M35='categories 2'!A$3,data!N35='categories 2'!B$3), AND(data!M35='categories 2'!A$4,data!N35='categories 2'!B$4), AND(data!M35='categories 2'!A$5,data!N35='categories 2'!B$5)), "aligned", "MISALIGNED") -> MISALIGNED
A36: 10.1037/dev0000374 | B36: Becht; Nelemans; Branje; Vollebergh; Koot; Meeus | C36: 2017 | D36: Identity uncertainty and commitment making across adolescence: Five-year within-person associations using daily identity reports. | E36: Developmental Psychology | F36: https://doi.org/10.1037/dev0000374 | G36: 37 | H36: 2 | I36: 1 | K36: 1 | L36: Utrecht-Management of Identity Commitments Scale (U-MICS; Klimstra et al., 2010); Single item | M36: Self report | N36: Subjective experience | O36: =IF(OR(AND(data!M36='categories 2'!A$2,data!N36='categories 2'!B$2), AND(data!M36='categories 2'!A$3,data!N36='categories 2'!B$3), AND(data!M36='categories 2'!A$4,data!N36='categories 2'!B$4), AND(data!M36='categories 2'!A$5,data!N36='categories 2'!B$5)), "aligned", "MISALIGNED") -> aligned
A37: 10.1037/emo0000021 | B37: Tamir; Bigman; Rhodes; Salerno; Schreier | C37: 2015 | D37: An expectancy-value model of emotion regulation: Implications for motivation, emotional experience, and decision making. | E37: Emotion | F37: https://doi.org/10.1037/emo0000021 | G37: 89 | H37: 1 | I37: 1 | K37: 1 | L37: Unnamed rating of concurrent emotions | M37: Self report | N37: Subjective experience | O37: =IF(OR(AND(data!M37='categories 2'!A$2,data!N37='categories 2'!B$2), AND(data!M37='categories 2'!A$3,data!N37='categories 2'!B$3), AND(data!M37='categories 2'!A$4,data!N37='categories 2'!B$4), AND(data!M37='categories 2'!A$5,data!N37='categories 2'!B$5)), "aligned", "MISALIGNED") -> aligned
I38: 1 | K38: 2 | L38: Unnamed rating of reading preference | M38: Self report | N38: Subjective experience | O38: =IF(OR(AND(data!M38='categories 2'!A$2,data!N38='categories 2'!B$2), AND(data!M38='categories 2'!A$3,data!N38='categories 2'!B$3), AND(data!M38='categories 2'!A$4,data!N38='categories 2'!B$4), AND(data!M38='categories 2'!A$5,data!N38='categories 2'!B$5)), "aligned", "MISALIGNED") -> aligned
A39: 10.1037/emo0001057 | B39: Lee; Lim; Lee | C39: 2022 | D39: Sharing joy increases joy: Group membership modulates emotional perception of facial expressions. | E39: Emotion | F39: https://doi.org/10.1037/emo0001057 | G39: 1 | H39: 2 | I39: 2 | K39: 1 | L39: Unnamed win/loss judgment task | M39: Test | N39: Mental ability or cognitive process | O39: =IF(OR(AND(data!M39='categories 2'!A$2,data!N39='categories 2'!B$2), AND(data!M39='categories 2'!A$3,data!N39='categories 2'!B$3), AND(data!M39='categories 2'!A$4,data!N39='categories 2'!B$4), AND(data!M39='categories 2'!A$5,data!N39='categories 2'!B$5)), "aligned", "MISALIGNED") -> aligned
I40: 2 | K40: 2 | L40: Unnamed emotional judgment task | M40: Self report | N40: Subjective experience | O40: =IF(OR(AND(data!M40='categories 2'!A$2,data!N40='categories 2'!B$2), AND(data!M40='categories 2'!A$3,data!N40='categories 2'!B$3), AND(data!M40='categories 2'!A$4,data!N40='categories 2'!B$4), AND(data!M40='categories 2'!A$5,data!N40='categories 2'!B$5)), "aligned", "MISALIGNED") -> aligned
A41: 10.1037/0021-9010.92.5.1254 | B41: Miner-Rubino; Cortina | C41: 2007 | D41: Beyond targets: Consequences of vicarious exposure to misogyny at work. | E41: Journal of Applied Psychology | F41: https://doi.org/10.1037/0021-9010.92.5.1254 | G41: 147 | H41: 1 | I41: 1 | K41: 1 | L41: Workplace Incivility Scale, adapted (WIS; Cortina et al., 2001) | M41: Self report | N41: Behavior | O41: =IF(OR(AND(data!M41='categories 2'!A$2,data!N41='categories 2'!B$2), AND(data!M41='categories 2'!A$3,data!N41='categories 2'!B$3), AND(data!M41='categories 2'!A$4,data!N41='categories 2'!B$4), AND(data!M41='categories 2'!A$5,data!N41='categories 2'!B$5)), "aligned", "MISALIGNED") -> MISALIGNED | P41: FALSE | Q41: Out of time
I42: 1 | K42: 2 | L42: Three items adapted from the Sexual Experiences Questionnaire (SEQ; Fitzgerald et al., 1988) | M42: Self report | N42: Behavior | O42: =IF(OR(AND(data!M42='categories 2'!A$2,data!N42='categories 2'!B$2), AND(data!M42='categories 2'!A$3,data!N42='categories 2'!B$3), AND(data!M42='categories 2'!A$4,data!N42='categories 2'!B$4), AND(data!M42='categories 2'!A$5,data!N42='categories 2'!B$5)), "aligned", "MISALIGNED") -> MISALIGNED | P42: FALSE | Q42: Out of time
I43: 1 | K43: 3 | L43: Nine questions about perceptions of university policies and practices regarding harassment (Langhout et al., 2000) | M43: Self report | N43: Out of time | O43: =IF(OR(AND(data!M43='categories 2'!A$2,data!N43='categories 2'!B$2), AND(data!M43='categories 2'!A$3,data!N43='categories 2'!B$3), AND(data!M43='categories 2'!A$4,data!N43='categories 2'!B$4), AND(data!M43='categories 2'!A$5,data!N43='categories 2'!B$5)), "aligned", "MISALIGNED") -> MISALIGNED
I44: 1 | K44: 4 | L44: Anxiety and Depression subscales of the Brief Symptom Inventory (Derogatis & Spencer, 1983) | M44: Self report | N44: Subjective experience | O44: =IF(OR(AND(data!M44='categories 2'!A$2,data!N44='categories 2'!B$2), AND(data!M44='categories 2'!A$3,data!N44='categories 2'!B$3), AND(data!M44='categories 2'!A$4,data!N44='categories 2'!B$4), AND(data!M44='categories 2'!A$5,data!N44='categories 2'!B$5)), "aligned", "MISALIGNED") -> aligned
I45: 1 | K45: 5 | L45: Physical well-being: assessed with three items adapted from work by Pennebaker (1982) | M45: Self report | N45: Neuro/bio/physiology | O45: =IF(OR(AND(data!M45='categories 2'!A$2,data!N45='categories 2'!B$2), AND(data!M45='categories 2'!A$3,data!N45='categories 2'!B$3), AND(data!M45='categories 2'!A$4,data!N45='categories 2'!B$4), AND(data!M45='categories 2'!A$5,data!N45='categories 2'!B$5)), "aligned", "MISALIGNED") -> MISALIGNED
I46: 1 | K46: 6 | L46: Three items from the Michigan Organizational Assessment Questionnaire | M46: Self report | N46: Subjective experience | O46: =IF(OR(AND(data!M46='categories 2'!A$2,data!N46='categories 2'!B$2), AND(data!M46='categories 2'!A$3,data!N46='categories 2'!B$3), AND(data!M46='categories 2'!A$4,data!N46='categories 2'!B$4), AND(data!M46='categories 2'!A$5,data!N46='categories 2'!B$5)), "aligned", "MISALIGNED") -> aligned
I47: 1 | K47: 7 | L47: Oldenburg Burnout Inventory (Demerouti, Bakker, Nachreiner, & Schaufeli, 2001) | M47: Self report | N47: Out of time | O47: =IF(OR(AND(data!M47='categories 2'!A$2,data!N47='categories 2'!B$2), AND(data!M47='categories 2'!A$3,data!N47='categories 2'!B$3), AND(data!M47='categories 2'!A$4,data!N47='categories 2'!B$4), AND(data!M47='categories 2'!A$5,data!N47='categories 2'!B$5)), "aligned", "MISALIGNED") -> MISALIGNED
I48: 1 | K48: 8 | L48: Job withdrawal (measured with Porter et al. (1976) two-item measure) | M48: Self report | N48: Subjective experience | O48: =IF(OR(AND(data!M48='categories 2'!A$2,data!N48='categories 2'!B$2), AND(data!M48='categories 2'!A$3,data!N48='categories 2'!B$3), AND(data!M48='categories 2'!A$4,data!N48='categories 2'!B$4), AND(data!M48='categories 2'!A$5,data!N48='categories 2'!B$5)), "aligned", "MISALIGNED") -> aligned
I49: 1 | K49: 9 | L49: Organizational affective commitment measure (Allen and Meyer, 1990) | M49: Self report | N49: Out of time | O49: =IF(OR(AND(data!M49='categories 2'!A$2,data!N49='categories 2'!B$2), AND(data!M49='categories 2'!A$3,data!N49='categories 2'!B$3), AND(data!M49='categories 2'!A$4,data!N49='categories 2'!B$4), AND(data!M49='categories 2'!A$5,data!N49='categories 2'!B$5)), "aligned", "MISALIGNED") -> MISALIGNED
I50: 1 | K50: 10 | L50: Life Orientation Test (Scheier & Carver, 1985) | M50: Self report | N50: Out of time | O50: =IF(OR(AND(data!M50='categories 2'!A$2,data!N50='categories 2'!B$2), AND(data!M50='categories 2'!A$3,data!N50='categories 2'!B$3), AND(data!M50='categories 2'!A$4,data!N50='categories 2'!B$4), AND(data!M50='categories 2'!A$5,data!N50='categories 2'!B$5)), "aligned", "MISALIGNED") -> MISALIGNED
A51: 10.1037/apl0000471 | B51: Aw; Ilies; De Pater | C51: 2020 | D51: Dispositional empathy, emotional display authenticity, and employee outcomes. | E51: Journal of Applied Psychology | F51: https://doi.org/10.1037/apl0000471 | H51: 2 | I51: 1 | K51: 1 | L51: Empathic Concern and Perspective Taking (subscales from the Interpersonal Reactivity Index; Davis, 1980) | M51: Self report | N51: Subjective experience | O51: =IF(OR(AND(data!M51='categories 2'!A$2,data!N51='categories 2'!B$2), AND(data!M51='categories 2'!A$3,data!N51='categories 2'!B$3), AND(data!M51='categories 2'!A$4,data!N51='categories 2'!B$4), AND(data!M51='categories 2'!A$5,data!N51='categories 2'!B$5)), "aligned", "MISALIGNED") -> aligned
I52: 1 | K52: 2 | L52: Challenge and hindrance stressors scale (Cavanaugh et al., 2000) | M52: Self report | N52: Subjective experience | O52: =IF(OR(AND(data!M52='categories 2'!A$2,data!N52='categories 2'!B$2), AND(data!M52='categories 2'!A$3,data!N52='categories 2'!B$3), AND(data!M52='categories 2'!A$4,data!N52='categories 2'!B$4), AND(data!M52='categories 2'!A$5,data!N52='categories 2'!B$5)), "aligned", "MISALIGNED") -> aligned
I53: 1 | K53: 3 | L53: Emotional display scales (Diefendorff et al., 2005) | M53: Self report | N53: Subjective experience | O53: =IF(OR(AND(data!M53='categories 2'!A$2,data!N53='categories 2'!B$2), AND(data!M53='categories 2'!A$3,data!N53='categories 2'!B$3), AND(data!M53='categories 2'!A$4,data!N53='categories 2'!B$4), AND(data!M53='categories 2'!A$5,data!N53='categories 2'!B$5)), "aligned", "MISALIGNED") -> aligned
I54: 1 | K54: 4 | L54: Job satisfaction scale (Brayfield & Rothe, 1951) | M54: Self report | N54: Subjective experience | O54: =IF(OR(AND(data!M54='categories 2'!A$2,data!N54='categories 2'!B$2), AND(data!M54='categories 2'!A$3,data!N54='categories 2'!B$3), AND(data!M54='categories 2'!A$4,data!N54='categories 2'!B$4), AND(data!M54='categories 2'!A$5,data!N54='categories 2'!B$5)), "aligned", "MISALIGNED") -> aligned
I55: 1 | K55: 5 | L55: Absenteeism: Number of days employees called in sick | M55: Behavioral (frequency, duration, latency) | N55: Behavior | O55: =IF(OR(AND(data!M55='categories 2'!A$2,data!N55='categories 2'!B$2), AND(data!M55='categories 2'!A$3,data!N55='categories 2'!B$3), AND(data!M55='categories 2'!A$4,data!N55='categories 2'!B$4), AND(data!M55='categories 2'!A$5,data!N55='categories 2'!B$5)), "aligned", "MISALIGNED") -> aligned | P55: FALSE | Q55: TRUE
I56: 1 | K56: 6 | L56: Performance | M56: Self report | N56: Out of time | O56: =IF(OR(AND(data!M56='categories 2'!A$2,data!N56='categories 2'!B$2), AND(data!M56='categories 2'!A$3,data!N56='categories 2'!B$3), AND(data!M56='categories 2'!A$4,data!N56='categories 2'!B$4), AND(data!M56='categories 2'!A$5,data!N56='categories 2'!B$5)), "aligned", "MISALIGNED") -> MISALIGNED
A57: 10.1080/15374416.2023.2222405 | B57: Hogue; MacLean; Bobek; Dunnsue; Porter; Jensen-Doss; Henderson | C57: 2023 | D57: Training Community Therapists in Core Elements of CBT and Family Therapy for Adolescent Externalizing Problems | E57: Journal of Clinical Child and Adolescent Psychology | F57: https://doi.org/10.1080/15374416.2023.2222405 | G57: 4 | H57: 1 | I57: 1 | K57: 1 | L57: Inventory of Therapy Techniques (ITT; Hogue et al., 2014, 2015) | M57: Self report | N57: Out of time | O57: =IF(OR(AND(data!M57='categories 2'!A$2,data!N57='categories 2'!B$2), AND(data!M57='categories 2'!A$3,data!N57='categories 2'!B$3), AND(data!M57='categories 2'!A$4,data!N57='categories 2'!B$4), AND(data!M57='categories 2'!A$5,data!N57='categories 2'!B$5)), "aligned", "MISALIGNED") -> MISALIGNED
I58: 1 | K58: 2 | L58: Inventory of Therapy Techniques: Observational Version (ITT-O) | M58: Self report | N58: Out of time | O58: =IF(OR(AND(data!M58='categories 2'!A$2,data!N58='categories 2'!B$2), AND(data!M58='categories 2'!A$3,data!N58='categories 2'!B$3), AND(data!M58='categories 2'!A$4,data!N58='categories 2'!B$4), AND(data!M58='categories 2'!A$5,data!N58='categories 2'!B$5)), "aligned", "MISALIGNED") -> MISALIGNED
A59: 10.1080/15374416.2012.654464 | B59: Fabiano; Pelham; Cunningham; Yu; Gangloff; Buck; Linke; Gormley; Gera | C59: 2012 | D59: A Waitlist-Controlled Trial of Behavioral Parent Training for Fathers of Children with ADHD | E59: Journal of Clinical Child and Adolescent Psychology | F59: https://doi.org/10.1080/15374416.2012.654464 | G59: 67 | H59: 2 | I59: 1 | K59: 1 | L59: Child Behavior Inventory (ECBI; Eyberg & Pincus, 1999) | M59: Self report | N59: Behavior | O59: =IF(OR(AND(data!M59='categories 2'!A$2,data!N59='categories 2'!B$2), AND(data!M59='categories 2'!A$3,data!N59='categories 2'!B$3), AND(data!M59='categories 2'!A$4,data!N59='categories 2'!B$4), AND(data!M59='categories 2'!A$5,data!N59='categories 2'!B$5)), "aligned", "MISALIGNED") -> MISALIGNED | P59: FALSE | Q59: TRUE
I60: 1 | K60: 2 | L60: Dyadic Parent–Child Interaction Coding System II (DPICS–II; Eyberg, Bessmer, Newcomb, Edwards, & Robinson, 1994) | M60: Behavioral (frequency, duration, latency) | N60: Behavior | O60: =IF(OR(AND(data!M60='categories 2'!A$2,data!N60='categories 2'!B$2), AND(data!M60='categories 2'!A$3,data!N60='categories 2'!B$3), AND(data!M60='categories 2'!A$4,data!N60='categories 2'!B$4), AND(data!M60='categories 2'!A$5,data!N60='categories 2'!B$5)), "aligned", "MISALIGNED") -> aligned | P60: FALSE | Q60: TRUE
I61: 1 | K61: 3 | L61: Therapy Attitude Inventory (TAI; Brestan, Jacobs, Rayfield, & Eyberg, 1999) | M61: Self report | N61: Subjective experience | O61: =IF(OR(AND(data!M61='categories 2'!A$2,data!N61='categories 2'!B$2), AND(data!M61='categories 2'!A$3,data!N61='categories 2'!B$3), AND(data!M61='categories 2'!A$4,data!N61='categories 2'!B$4), AND(data!M61='categories 2'!A$5,data!N61='categories 2'!B$5)), "aligned", "MISALIGNED") -> aligned
A62: 10.1037/a0035536 | B62: Sergeant; Mongrain | C62: 2014 | D62: An online optimism intervention reduces depression in pessimistic individuals. | E62: Journal of Consulting and Clinical Psychology | F62: https://doi.org/10.1037/a0035536 | G62: 55 | H62: 1 | I62: 1 | K62: 1 | L62: Centre for Epidemiological Studies Depression Scale (CES-D; Radloff, 1977) | M62: Self report | N62: Behavior | O62: =IF(OR(AND(data!M62='categories 2'!A$2,data!N62='categories 2'!B$2), AND(data!M62='categories 2'!A$3,data!N62='categories 2'!B$3), AND(data!M62='categories 2'!A$4,data!N62='categories 2'!B$4), AND(data!M62='categories 2'!A$5,data!N62='categories 2'!B$5)), "aligned", "MISALIGNED") -> MISALIGNED | P62: FALSE | Q62: TRUE
I63: 1 | K63: 2 | L63: Dysfunctional Attitude Scale–14 (DAS-14; Mongrain & Zuroff, 1989) | M63: Self report | N63: Subjective experience | O63: =IF(OR(AND(data!M63='categories 2'!A$2,data!N63='categories 2'!B$2), AND(data!M63='categories 2'!A$3,data!N63='categories 2'!B$3), AND(data!M63='categories 2'!A$4,data!N63='categories 2'!B$4), AND(data!M63='categories 2'!A$5,data!N63='categories 2'!B$5)), "aligned", "MISALIGNED") -> aligned
I64: 1 | K64: 3 | L64: Life Orientation Test–Revised (LOT-R; Scheier et al., 1994) | M64: Self report | N64: Subjective experience | O64: =IF(OR(AND(data!M64='categories 2'!A$2,data!N64='categories 2'!B$2), AND(data!M64='categories 2'!A$3,data!N64='categories 2'!B$3), AND(data!M64='categories 2'!A$4,data!N64='categories 2'!B$4), AND(data!M64='categories 2'!A$5,data!N64='categories 2'!B$5)), "aligned", "MISALIGNED") -> aligned
I65: 1 | K65: 4 | L65: Orientations to Happiness (OTH; Peterson, Park, & Seligman, 2005) | M65: Self report | N65: Subjective experience | O65: =IF(OR(AND(data!M65='categories 2'!A$2,data!N65='categories 2'!B$2), AND(data!M65='categories 2'!A$3,data!N65='categories 2'!B$3), AND(data!M65='categories 2'!A$4,data!N65='categories 2'!B$4), AND(data!M65='categories 2'!A$5,data!N65='categories 2'!B$5)), "aligned", "MISALIGNED") -> aligned
A66: 10.1037/a0028032 | B66: Meuret; Seidel; Rosenfield; Hofmann; Rosenfield | C66: 2012 | D66: Does fear reactivity during exposure predict panic symptom reduction? | E66: Journal of Consulting and Clinical Psychology | F66: https://doi.org/10.1037/a0028032 | G66: 46 | H66: 2 | I66: 1 | J66: Semi-structured interview | K66: 1 | L66: Panic Disorder Severity Scale (PDSS; Shear et al., 1997) | M66: Self report | N66: Behavior | O66: =IF(OR(AND(data!M66='categories 2'!A$2,data!N66='categories 2'!B$2), AND(data!M66='categories 2'!A$3,data!N66='categories 2'!B$3), AND(data!M66='categories 2'!A$4,data!N66='categories 2'!B$4), AND(data!M66='categories 2'!A$5,data!N66='categories 2'!B$5)), "aligned", "MISALIGNED") -> MISALIGNED
I67: 1 | K67: 2 | L67: Anxiety Sensitivity Index (ASI; Reiss, Peterson, Gursky, & McNally, 1986) | M67: Self report | N67: Subjective experience | O67: =IF(OR(AND(data!M67='categories 2'!A$2,data!N67='categories 2'!B$2), AND(data!M67='categories 2'!A$3,data!N67='categories 2'!B$3), AND(data!M67='categories 2'!A$4,data!N67='categories 2'!B$4), AND(data!M67='categories 2'!A$5,data!N67='categories 2'!B$5)), "aligned", "MISALIGNED") -> aligned
I68: 1 | K68: 3 | L68: Body Sensations Questionnaire (BSQ; Chambless, Caputo, Bright, & Gallagher, 1984) | M68: Self report | N68: Subjective experience | O68: =IF(OR(AND(data!M68='categories 2'!A$2,data!N68='categories 2'!B$2), AND(data!M68='categories 2'!A$3,data!N68='categories 2'!B$3), AND(data!M68='categories 2'!A$4,data!N68='categories 2'!B$4), AND(data!M68='categories 2'!A$5,data!N68='categories 2'!B$5)), "aligned", "MISALIGNED") -> aligned
I69: 1 | K69: 4 | L69: Mobility Inventory for Agoraphobia (MI–AAL; Chambless, Caputo, Jasin, Gracely, & Williams, 1985) | M69: Self report | N69: Behavior | O69: =IF(OR(AND(data!M69='categories 2'!A$2,data!N69='categories 2'!B$2), AND(data!M69='categories 2'!A$3,data!N69='categories 2'!B$3), AND(data!M69='categories 2'!A$4,data!N69='categories 2'!B$4), AND(data!M69='categories 2'!A$5,data!N69='categories 2'!B$5)), "aligned", "MISALIGNED") -> MISALIGNED | P69: FALSE | Q69: Out of time
I70: 1 | K70: 5 | L70: Anxiety Control Scale (ACS; Rapee, Craske, Brown, & Barlow, 1996) | M70: Self report | N70: Behavior | O70: =IF(OR(AND(data!M70='categories 2'!A$2,data!N70='categories 2'!B$2), AND(data!M70='categories 2'!A$3,data!N70='categories 2'!B$3), AND(data!M70='categories 2'!A$4,data!N70='categories 2'!B$4), AND(data!M70='categories 2'!A$5,data!N70='categories 2'!B$5)), "aligned", "MISALIGNED") -> MISALIGNED | P70: FALSE | Q70: Out of time
I71: 1 | K71: 6 | L71: Portable, battery-run capnometry device to collect Cardiorespiratory data | M71: Neuro/bio/physiological | N71: Neuro/bio/physiology | O71: =IF(OR(AND(data!M71='categories 2'!A$2,data!N71='categories 2'!B$2), AND(data!M71='categories 2'!A$3,data!N71='categories 2'!B$3), AND(data!M71='categories 2'!A$4,data!N71='categories 2'!B$4), AND(data!M71='categories 2'!A$5,data!N71='categories 2'!B$5)), "aligned", "MISALIGNED") -> aligned
I72: 1 | K72: 7 | L72: Unnamed self-report exposure log for intensity of DSM–IV panic symptoms. | M72: Self report | N72: Subjective experience | O72: =IF(OR(AND(data!M72='categories 2'!A$2,data!N72='categories 2'!B$2), AND(data!M72='categories 2'!A$3,data!N72='categories 2'!B$3), AND(data!M72='categories 2'!A$4,data!N72='categories 2'!B$4), AND(data!M72='categories 2'!A$5,data!N72='categories 2'!B$5)), "aligned", "MISALIGNED") -> aligned
I73: 1 | K73: 8 | L73: Unnamed single-item scale for anxiety | M73: Self report | N73: Subjective experience | O73: =IF(OR(AND(data!M73='categories 2'!A$2,data!N73='categories 2'!B$2), AND(data!M73='categories 2'!A$3,data!N73='categories 2'!B$3), AND(data!M73='categories 2'!A$4,data!N73='categories 2'!B$4), AND(data!M73='categories 2'!A$5,data!N73='categories 2'!B$5)), "aligned", "MISALIGNED") -> aligned
A74: 10.1016/j.jecp.2014.11.001 | B74: Nayar; Franchak; Adolph; Kiorpes | C74: 2015 | D74: From local to global processing: The development of illusory contour perception | E74: Journal of Experimental Child Psychology | F74: https://doi.org/10.1016/j.jecp.2014.11.001 | G74: 36 | H74: 1 | I74: 1 | K74: 1 | L74: Looking and manual behaviors using a Positive Science head-mounted eye tracker | M74: Behavioral (frequency, duration, latency) | N74: Behavior | O74: =IF(OR(AND(data!M74='categories 2'!A$2,data!N74='categories 2'!B$2), AND(data!M74='categories 2'!A$3,data!N74='categories 2'!B$3), AND(data!M74='categories 2'!A$4,data!N74='categories 2'!B$4), AND(data!M74='categories 2'!A$5,data!N74='categories 2'!B$5)), "aligned", "MISALIGNED") -> aligned | P74: FALSE | Q74: TRUE
I75: 1 | K75: 2 | L75: Accuracy of responses in shape task | M75: Test | N75: Mental ability or cognitive process | O75: =IF(OR(AND(data!M75='categories 2'!A$2,data!N75='categories 2'!B$2), AND(data!M75='categories 2'!A$3,data!N75='categories 2'!B$3), AND(data!M75='categories 2'!A$4,data!N75='categories 2'!B$4), AND(data!M75='categories 2'!A$5,data!N75='categories 2'!B$5)), "aligned", "MISALIGNED") -> aligned
A76: 10.1016/j.jecp.2012.06.008 | B76: Blake; Ganea; Harris | C76: 2012 | D76: Possession is not always the law: With age, preschoolers increasingly use verbal information to identify who owns what | E76: Journal of Experimental Child Psychology | F76: https://doi.org/10.1016/j.jecp.2012.06.008 | G76: 35 | H76: 2 | I76: 2 | K76: 1 | L76: Measure of accuracy in responding to questions (‘‘Whose ball is it?’’ and ‘‘Who can keep the ball?’’) | M76: Test | N76: Mental ability or cognitive process | O76: =IF(OR(AND(data!M76='categories 2'!A$2,data!N76='categories 2'!B$2), AND(data!M76='categories 2'!A$3,data!N76='categories 2'!B$3), AND(data!M76='categories 2'!A$4,data!N76='categories 2'!B$4), AND(data!M76='categories 2'!A$5,data!N76='categories 2'!B$5)), "aligned", "MISALIGNED") -> aligned
A77: 10.1037/xap0000518 | B77: Patel; Yang; Steyvers; Benjamin | C77: 2024 | D77: The metacognition of vigilance: Using self-scheduled breaks to improve sustained attention. | E77: Journal of Experimental Psychology: Applied | F77: https://doi.org/10.1037/xap0000518 | G77: 0 | H77: 1 | I77: 1 | K77: 1 | L77: Vigilance task (Helton & Russell, 2013). | M77: Test | N77: Mental ability or cognitive process | O77: =IF(OR(AND(data!M77='categories 2'!A$2,data!N77='categories 2'!B$2), AND(data!M77='categories 2'!A$3,data!N77='categories 2'!B$3), AND(data!M77='categories 2'!A$4,data!N77='categories 2'!B$4), AND(data!M77='categories 2'!A$5,data!N77='categories 2'!B$5)), "aligned", "MISALIGNED") -> aligned
I78: 1 | K78: 2 | L78: Breaks taken | M78: Behavioral (frequency, duration, latency) | N78: Behavior | O78: =IF(OR(AND(data!M78='categories 2'!A$2,data!N78='categories 2'!B$2), AND(data!M78='categories 2'!A$3,data!N78='categories 2'!B$3), AND(data!M78='categories 2'!A$4,data!N78='categories 2'!B$4), AND(data!M78='categories 2'!A$5,data!N78='categories 2'!B$5)), "aligned", "MISALIGNED") -> aligned | P78: FALSE | Q78: TRUE
A79: 10.1037/xap0000451 | B79: Inbar; Waldhof | C79: 2023 | D79: Mitigating consequence insensitivity for genetically engineered crops. | E79: Journal of Experimental Psychology: Applied | F79: https://doi.org/10.1037/xap0000451 | G79: 2 | H79: 2 | I79: 1 | K79: 1 | L79: Unnamed question + Likert scale regarding attitudes toward GE crops | M79: Self report | N79: Subjective experience | O79: =IF(OR(AND(data!M79='categories 2'!A$2,data!N79='categories 2'!B$2), AND(data!M79='categories 2'!A$3,data!N79='categories 2'!B$3), AND(data!M79='categories 2'!A$4,data!N79='categories 2'!B$4), AND(data!M79='categories 2'!A$5,data!N79='categories 2'!B$5)), "aligned", "MISALIGNED") -> aligned
I80: 1 | K80: 2 | L80: Unnamed consequence‐insensitivity beliefs items | M80: Self report | N80: Subjective experience | O80: =IF(OR(AND(data!M80='categories 2'!A$2,data!N80='categories 2'!B$2), AND(data!M80='categories 2'!A$3,data!N80='categories 2'!B$3), AND(data!M80='categories 2'!A$4,data!N80='categories 2'!B$4), AND(data!M80='categories 2'!A$5,data!N80='categories 2'!B$5)), "aligned", "MISALIGNED") -> aligned
I81: 1 | K81: 3 | L81: Four moral conviction items, adapted from Skitka et al. (2005) | M81: Self report | N81: Subjective experience | O81: =IF(OR(AND(data!M81='categories 2'!A$2,data!N81='categories 2'!B$2), AND(data!M81='categories 2'!A$3,data!N81='categories 2'!B$3), AND(data!M81='categories 2'!A$4,data!N81='categories 2'!B$4), AND(data!M81='categories 2'!A$5,data!N81='categories 2'!B$5)), "aligned", "MISALIGNED") -> aligned
I82: 1 | K82: 4 | L82: Belief Probes (one of four: Open-Ended Reflection; Risk and Benefits; Counterexamples; Hiden Consequentialism) | M82: Self report | N82: Subjective experience | O82: =IF(OR(AND(data!M82='categories 2'!A$2,data!N82='categories 2'!B$2), AND(data!M82='categories 2'!A$3,data!N82='categories 2'!B$3), AND(data!M82='categories 2'!A$4,data!N82='categories 2'!B$4), AND(data!M82='categories 2'!A$5,data!N82='categories 2'!B$5)), "aligned", "MISALIGNED") -> aligned
A83: 10.1037/xge0000128 | B83: Fawcett; Lawrence; Taylor | C83: 2016 | D83: The representational consequences of intentional forgetting: Impairments to both the probability and fidelity of long-term memory. | E83: Journal of Experimental Psychology: General | F83: https://doi.org/10.1037/xge0000128 | G83: 52 | H83: 1 | I83: 1 | K83: 1 | L83: Old-New Recognition Accuracy | M83: Test | N83: Mental ability or cognitive process | O83: =IF(OR(AND(data!M83='categories 2'!A$2,data!N83='categories 2'!B$2), AND(data!M83='categories 2'!A$3,data!N83='categories 2'!B$3), AND(data!M83='categories 2'!A$4,data!N83='categories 2'!B$4), AND(data!M83='categories 2'!A$5,data!N83='categories 2'!B$5)), "aligned", "MISALIGNED") -> aligned
A84: 10.1037/xge0000706 | B84: Scheerer; Jacobson; Jones | C84: 2020 | D84: Sensorimotor control of vocal production in early childhood. | E84: Journal of Experimental Psychology: General | F84: https://doi.org/10.1037/xge0000706 | G84: 5 | H84: 2 | I84: 1 | J84: This could be split into multiple aspects but those are only derived, so I'm very unsure here | K84: 1 | L84: (F0 values) Acoustic measures of pitch control and feedback response | M84: Indeterminable | N84: Indeterminable | O84: =IF(OR(AND(data!M84='categories 2'!A$2,data!N84='categories 2'!B$2), AND(data!M84='categories 2'!A$3,data!N84='categories 2'!B$3), AND(data!M84='categories 2'!A$4,data!N84='categories 2'!B$4), AND(data!M84='categories 2'!A$5,data!N84='categories 2'!B$5)), "aligned", "MISALIGNED") -> MISALIGNED
A85: 10.1037/xhp0000628 | B85: Searston; Thompson; Vokey; French; Tangen | C85: 2019 | D85: How low can you go? Detecting style in extremely low resolution images. | E85: Journal of Experimental Psychology: Human Perception and Performance | F85: https://doi.org/10.1037/xhp0000628 | G85: 4 | H85: 1 | I85: 2 | J85: Unsure | K85: 1 | L85: Discrimination task | M85: Self report | N85: Mental ability or cognitive process | O85: =IF(OR(AND(data!M85='categories 2'!A$2,data!N85='categories 2'!B$2), AND(data!M85='categories 2'!A$3,data!N85='categories 2'!B$3), AND(data!M85='categories 2'!A$4,data!N85='categories 2'!B$4), AND(data!M85='categories 2'!A$5,data!N85='categories 2'!B$5)), "aligned", "MISALIGNED") -> MISALIGNED
A86: 10.1037/xhp0000339 | B86: Livingstone; Christie; Wright; McDonald | C86: 2017 | D86: Signal enhancement, not active suppression, follows the contingent capture of visual attention. | E86: Journal of Experimental Psychology: Human Perception and Performance | F86: https://doi.org/10.1037/xhp0000339 | G86: 22 | H86: 2 | I86: 1 | K86: 1 | L86: Response times | M86: Behavioral (frequency, duration, latency) | N86: Behavior | O86: =IF(OR(AND(data!M86='categories 2'!A$2,data!N86='categories 2'!B$2), AND(data!M86='categories 2'!A$3,data!N86='categories 2'!B$3), AND(data!M86='categories 2'!A$4,data!N86='categories 2'!B$4), AND(data!M86='categories 2'!A$5,data!N86='categories 2'!B$5)), "aligned", "MISALIGNED") -> aligned | P86: Out of time | Q86: Out of time
I87: 1 | K87: 2 | L87: EEG | M87: Neuro/bio/physiological | N87: Mental ability or cognitive process | O87: =IF(OR(AND(data!M87='categories 2'!A$2,data!N87='categories 2'!B$2), AND(data!M87='categories 2'!A$3,data!N87='categories 2'!B$3), AND(data!M87='categories 2'!A$4,data!N87='categories 2'!B$4), AND(data!M87='categories 2'!A$5,data!N87='categories 2'!B$5)), "aligned", "MISALIGNED") -> MISALIGNED
A88: 10.1037/xlm0000994 | B88: Kreiner; Gamliel | C88: 2022 | D88: Framing fake news: Asymmetric attribute-framing bias for favorable and unfavorable outcomes. | E88: Journal of Experimental Psychology: Learning, Memory, and Cognition | F88: https://doi.org/10.1037/xlm0000994 | G88: 1 | H88: 1 | I88: 1 | K88: 1 | L88: Estimation of true/fake news encounters | M88: Self report | N88: Subjective experience | O88: =IF(OR(AND(data!M88='categories 2'!A$2,data!N88='categories 2'!B$2), AND(data!M88='categories 2'!A$3,data!N88='categories 2'!B$3), AND(data!M88='categories 2'!A$4,data!N88='categories 2'!B$4), AND(data!M88='categories 2'!A$5,data!N88='categories 2'!B$5)), "aligned", "MISALIGNED") -> aligned
I89: 1 | K89: 2 | L89: Three evaluation likert scales ("How would you describe this news item?", "How would you evaluate this news item?", "How would you regard this news item?") | M89: Self report | N89: Subjective experience | O89: =IF(OR(AND(data!M89='categories 2'!A$2,data!N89='categories 2'!B$2), AND(data!M89='categories 2'!A$3,data!N89='categories 2'!B$3), AND(data!M89='categories 2'!A$4,data!N89='categories 2'!B$4), AND(data!M89='categories 2'!A$5,data!N89='categories 2'!B$5)), "aligned", "MISALIGNED") -> aligned
A90: 10.1037/xlm0000805 | B90: Jesse | C90: 2021 | D90: Sentence context guides phonetic retuning to speaker idiosyncrasies. | E90: Journal of Experimental Psychology: Learning, Memory, and Cognition | F90: https://doi.org/10.1037/xlm0000805 | G90: 7 | H90: 2 | I90: 3 | K90: 1 | L90: Cloze probability | M90: Test | N90: Mental ability or cognitive process | O90: =IF(OR(AND(data!M90='categories 2'!A$2,data!N90='categories 2'!B$2), AND(data!M90='categories 2'!A$3,data!N90='categories 2'!B$3), AND(data!M90='categories 2'!A$4,data!N90='categories 2'!B$4), AND(data!M90='categories 2'!A$5,data!N90='categories 2'!B$5)), "aligned", "MISALIGNED") -> aligned
I91: 3 | K91: 2 | L91: Percentage of [s] responses | M91: Test | N91: Mental ability or cognitive process | O91: =IF(OR(AND(data!M91='categories 2'!A$2,data!N91='categories 2'!B$2), AND(data!M91='categories 2'!A$3,data!N91='categories 2'!B$3), AND(data!M91='categories 2'!A$4,data!N91='categories 2'!B$4), AND(data!M91='categories 2'!A$5,data!N91='categories 2'!B$5)), "aligned", "MISALIGNED") -> aligned
A92: 10.1016/j.jesp.2010.11.005 | B92: Forgas | C92: 2011 | D92: Can negative affect eliminate the power of first impressions? Affective influences on primacy and recency effects in impression formation | E92: Journal of Experimental Social Psychology | F92: http+B153:G153s://doi.org/10.1016/j.jesp.2010.11.005 | G92: 72 | H92: 1 | I92: 1 | K92: 1 | L92: Social Judgement Task | M92: Self report | N92: Subjective experience | O92: =IF(OR(AND(data!M92='categories 2'!A$2,data!N92='categories 2'!B$2), AND(data!M92='categories 2'!A$3,data!N92='categories 2'!B$3), AND(data!M92='categories 2'!A$4,data!N92='categories 2'!B$4), AND(data!M92='categories 2'!A$5,data!N92='categories 2'!B$5)), "aligned", "MISALIGNED") -> aligned
A93: 10.1016/j.jesp.2022.104375 | B93: Fernández; Gaviria; Halperin; Agudo; González-Puerto; Chas-Villar; Saguy | C93: 2022 | D93: The protective effect of agency on victims of humiliation | E93: Journal of Experimental Social Psychology | F93: https://doi.org/10.1016/j.jesp.2022.104375 | G93: 3 | H93: 2 | I93: 2 | K93: 1 | L93: Unnamed likert scale: Internalization of the devaluation | M93: Self report | N93: Subjective experience | O93: =IF(OR(AND(data!M93='categories 2'!A$2,data!N93='categories 2'!B$2), AND(data!M93='categories 2'!A$3,data!N93='categories 2'!B$3), AND(data!M93='categories 2'!A$4,data!N93='categories 2'!B$4), AND(data!M93='categories 2'!A$5,data!N93='categories 2'!B$5)), "aligned", "MISALIGNED") -> aligned
I94: 2 | K94: 2 | L94: Unnamed likert scale: Unfairness Appraisal | M94: Self report | N94: Subjective experience | O94: =IF(OR(AND(data!M94='categories 2'!A$2,data!N94='categories 2'!B$2), AND(data!M94='categories 2'!A$3,data!N94='categories 2'!B$3), AND(data!M94='categories 2'!A$4,data!N94='categories 2'!B$4), AND(data!M94='categories 2'!A$5,data!N94='categories 2'!B$5)), "aligned", "MISALIGNED") -> aligned
I95: 2 | K95: 3 | L95: Unnamed likert scale: Felt Emotions | M95: Self report | N95: Subjective experience | O95: =IF(OR(AND(data!M95='categories 2'!A$2,data!N95='categories 2'!B$2), AND(data!M95='categories 2'!A$3,data!N95='categories 2'!B$3), AND(data!M95='categories 2'!A$4,data!N95='categories 2'!B$4), AND(data!M95='categories 2'!A$5,data!N95='categories 2'!B$5)), "aligned", "MISALIGNED") -> aligned
A96: 10.1016/j.jml.2022.104374 | B96: Kumarage; Donnelly; Kidd | C96: 2022 | D96: Implicit learning of structure across time: A longitudinal investigation of syntactic priming in young English-acquiring children | E96: Journal of Memory and Language | F96: https://doi.org/10.1016/j.jml.2022.104374 | G96: 10 | H96: 1 | I96: 1 | K96: 1 | L96: MacArthur-Bates Communicative Development Inventories (Donnelly & Kidd, 2021) | M96: Self report | N96: Behavior | O96: =IF(OR(AND(data!M96='categories 2'!A$2,data!N96='categories 2'!B$2), AND(data!M96='categories 2'!A$3,data!N96='categories 2'!B$3), AND(data!M96='categories 2'!A$4,data!N96='categories 2'!B$4), AND(data!M96='categories 2'!A$5,data!N96='categories 2'!B$5)), "aligned", "MISALIGNED") -> MISALIGNED | P96: FALSE | Q96: FALSE
I97: 1 | K97: 2 | L97: Words and Sentences form (Fenson et al., 2007) | M97: Self report | N97: Behavior | O97: =IF(OR(AND(data!M97='categories 2'!A$2,data!N97='categories 2'!B$2), AND(data!M97='categories 2'!A$3,data!N97='categories 2'!B$3), AND(data!M97='categories 2'!A$4,data!N97='categories 2'!B$4), AND(data!M97='categories 2'!A$5,data!N97='categories 2'!B$5)), "aligned", "MISALIGNED") -> MISALIGNED | P97: FALSE | Q97: FALSE
I98: 1 | K98: 3 | L98: Verb matching "task" | M98: Test | N98: Behavior | O98: =IF(OR(AND(data!M98='categories 2'!A$2,data!N98='categories 2'!B$2), AND(data!M98='categories 2'!A$3,data!N98='categories 2'!B$3), AND(data!M98='categories 2'!A$4,data!N98='categories 2'!B$4), AND(data!M98='categories 2'!A$5,data!N98='categories 2'!B$5)), "aligned", "MISALIGNED") -> MISALIGNED | P98: FALSE | Q98: TRUE
A99: 10.1016/j.jml.2009.11.004 | B99: Zimmerman; Kelley | C99: 2010 | D99: “I’ll remember this!” Effects of emotionality on memory predictions versus memory performance | E99: Journal of Memory and Language | F99: https://doi.org/10.1016/j.jml.2009.11.004 | G99: 90 | H99: 2 | I99: 2 | K99: 1 | L99: Judgment of learning scale | M99: Self report | N99: Subjective experience | O99: =IF(OR(AND(data!M99='categories 2'!A$2,data!N99='categories 2'!B$2), AND(data!M99='categories 2'!A$3,data!N99='categories 2'!B$3), AND(data!M99='categories 2'!A$4,data!N99='categories 2'!B$4), AND(data!M99='categories 2'!A$5,data!N99='categories 2'!B$5)), "aligned", "MISALIGNED") -> aligned
I100: 2 | K100: 2 | L100: Recall test | M100: Test | N100: Mental ability or cognitive process | O100: =IF(OR(AND(data!M100='categories 2'!A$2,data!N100='categories 2'!B$2), AND(data!M100='categories 2'!A$3,data!N100='categories 2'!B$3), AND(data!M100='categories 2'!A$4,data!N100='categories 2'!B$4), AND(data!M100='categories 2'!A$5,data!N100='categories 2'!B$5)), "aligned", "MISALIGNED") -> aligned
...

Sheet categories
A1: category | B1: example
A2: Self-report of subjective experience | B2: Self-reported fear of spiders
A3: Subjective experience test | B3: Visual search test for synesthesia
A4: Behavioral measure of subjective experience | B4: Implicit racial bias
A5: Neuro/bio/physiological measure of subjective experience | B5: GSR as a measure of fear
A6: Self-report of ability | B6: Self-reported intelligence, self-reported empathic perspective taking ability
A7: Cognitive ability test | B7: Mental rotation test, N-back task
A8: Behavioral measure of ability | B8: Iowa Gambling Task
A9: Neuro/bio/physiological measure of ability | B9: Cognitive Control Capacity measured via fMRI
A10: Self-report of behavior | B10: Self-reported social media use
A11: Behavioral test | B11: Stimulus equivalence test
A12: Behavioral measure of behavior | B12: Social media use via digital trace data, observational coding
... A17: Neuro/bio/physiological measure of neuro/bio/physiology | B17: Structural MRI, Salivatory immunoassays to measure menstrual cycle phase
A18: Indeterminable

Sheet categories 2
A1: How it is measured | B1: What is measured | C1: Boolean | D1: Alignment
A2: Self report | B2: Subjective experience | C2: TRUE | D2: aligned
A3: Test | B3: Mental ability or cognitive process | C3: FALSE | D3: MISALIGNED
A4: Behavioral (frequency, duration, latency) | B4: Behavior | C4: Indeterminable
A5: Neuro/bio/physiological | B5: Neuro/bio/physiology | C5: Out of time
A6: Indeterminable | B6: Indeterminable
A7: Out of time | B7: Out of time
A11: old
A12: Self-report or other report | B12: Subjective experience (mental content, often self-perceived)
A13: Test (has correct answers) | B13: Mental ability or cognitive process
A14: Behavioral measure (non-self-report; captures frequency, duration or latency of overt behaviors) | B14: Behavior (specific overt behaviors)
A15: Neuro/bio/physiological measure | B15: Neuro/bio/physiology
A16: Indeterminable | B16: Indeterminable
